cubaflixmax/__init__.py
cubaflixmax/version.py
cubaflixmax-4.0.2.dist-info/LICENSE
cubaflixmax-4.0.2.dist-info/METADATA
cubaflixmax-4.0.2.dist-info/WHEEL
cubaflixmax-4.0.2.dist-info/top_level.txt
cubaflixmax-4.0.2.dist-info/zip-safe
cubaflixmax-4.0.2.dist-info/RECORD
